esc/__init__.py
esc/point_distance.py
esc/point_segment.py
esc/trajectory_distance.py
esc/trajectory_process.py
esc/area_extend/__init__.py
esc/area_extend/area_extend.py
esc/area_extend/extend_main.py
esc/area_extend/geodesic_buffer.py
esc/area_extend/others.py
esc/area_extend/test.py
esc/area_extend/translate.py
earth_surface_calculations-4.2.0.dist-info/METADATA
earth_surface_calculations-4.2.0.dist-info/WHEEL
earth_surface_calculations-4.2.0.dist-info/top_level.txt
earth_surface_calculations-4.2.0.dist-info/RECORD
