Metadata-Version: 2.1
Name: earth-surface-calculations
Version: 4.2.0
Summary: Geospatial utilities for Earth surface calculations
Author: Hanry Zhang
Author-email: popdoking@gmail.com
Classifier: Programming Language :: Python :: 3
Classifier: License :: OSI Approved :: MIT License
Classifier: Operating System :: OS Independent
Requires-Python: >=3.6
Requires-Dist: scipy
Requires-Dist: numpy
